liftcord/__init__.py
liftcord/__main__.py
liftcord/_types.py
liftcord/abc.py
liftcord/activity.py
liftcord/appinfo.py
liftcord/asset.py
liftcord/audit_logs.py
liftcord/automod.py
liftcord/backoff.py
liftcord/channel.py
liftcord/client.py
liftcord/colour.py
liftcord/components.py
liftcord/context_managers.py
liftcord/embeds.py
liftcord/emoji.py
liftcord/enums.py
liftcord/errors.py
liftcord/file.py
liftcord/flags.py
liftcord/gateway.py
liftcord/guild.py
liftcord/http.py
liftcord/integrations.py
liftcord/interactions.py
liftcord/invite.py
liftcord/member.py
liftcord/mentions.py
liftcord/message.py
liftcord/mixins.py
liftcord/object.py
liftcord/oggparse.py
liftcord/opus.py
liftcord/partial_emoji.py
liftcord/permissions.py
liftcord/player.py
liftcord/pylogz.py
liftcord/raw_models.py
liftcord/reaction.py
liftcord/role.py
liftcord/scheduled_event.py
liftcord/shard.py
liftcord/stage_instance.py
liftcord/state.py
liftcord/sticker.py
liftcord/team.py
liftcord/template.py
liftcord/threads.py
liftcord/user.py
liftcord/utils.py
liftcord/voice_client.py
liftcord/welcome_screen.py
liftcord/widget.py
liftcord/app_commands/__init__.py
liftcord/app_commands/checks.py
liftcord/app_commands/commands.py
liftcord/app_commands/errors.py
liftcord/app_commands/models.py
liftcord/app_commands/namespace.py
liftcord/app_commands/transformers.py
liftcord/app_commands/translator.py
liftcord/app_commands/tree.py
liftcord/ext/commands/__init__.py
liftcord/ext/commands/_types.py
liftcord/ext/commands/bot.py
liftcord/ext/commands/cog.py
liftcord/ext/commands/context.py
liftcord/ext/commands/converter.py
liftcord/ext/commands/cooldowns.py
liftcord/ext/commands/core.py
liftcord/ext/commands/errors.py
liftcord/ext/commands/flags.py
liftcord/ext/commands/help.py
liftcord/ext/commands/hybrid.py
liftcord/ext/commands/parameters.py
liftcord/ext/commands/view.py
liftcord/ext/tasks/__init__.py
liftcord/mobile/__init__.py
liftcord/types/__init__.py
liftcord/types/activity.py
liftcord/types/appinfo.py
liftcord-26.2.dist-info/METADATA
liftcord-26.2.dist-info/WHEEL
liftcord-26.2.dist-info/top_level.txt
liftcord-26.2.dist-info/RECORD
